alt_bucket-0.0.2.dist-info/DESCRIPTION.rst
alt_bucket-0.0.2.dist-info/METADATA
alt_bucket-0.0.2.dist-info/RECORD
alt_bucket-0.0.2.dist-info/WHEEL
alt_bucket-0.0.2.dist-info/metadata.json
alt_bucket-0.0.2.dist-info/top_level.txt
bucket/__init__.py
bucket/bootstrap.py
bucket/config/__init__.py
bucket/config/default_settings.py
bucket/feature/__init__.py
bucket/feature/debug_toolbar.py
bucket/feature/orm.py
