Metadata-Version: 2.0
Name: alt-bucket
Version: 0.0.2
Summary: The common package
Home-page: https://github.com/altaid/bucket
Author: Astafev Alexey
Author-email: efsneiron@gmail.com
License: MIT License
Keywords: python3,flask,orm,sqlalchemy,webapp
Platform: UNKNOWN
Classifier: Development Status :: 3 - Alpha
Classifier: Intended Audience :: Developers
Classifier: Intended Audience :: Information Technology
Classifier: License :: OSI Approved :: MIT License
Classifier: Programming Language :: Python :: 3
Classifier: Environment :: Web Environment
Classifier: Framework :: Flask
Classifier: Topic :: Internet :: WWW/HTTP :: Site Management
Classifier: Topic :: Software Development :: Libraries
Classifier: Topic :: Utilities
